Metadata-Version: 2.1
Name: Bestpackage3
Version: 0.1.3
Summary: To be the                 best
Author: Goog
Author-email: your_email@example.com
